jupyter_references/__init__.py
jupyter_references-0.7.dist-info/LICENSE
jupyter_references-0.7.dist-info/METADATA
jupyter_references-0.7.dist-info/WHEEL
jupyter_references-0.7.dist-info/top_level.txt
jupyter_references-0.7.dist-info/RECORD
