Metadata-Version: 2.1
Name: jupyter-references
Version: 0.7
Summary: Lightweight system for citing papers and making a reference list in jupyter
Home-page: https://github.com/kaspermunch/jupyter-references
Author: Kasper Munch
Author-email: kaspermunch@birc.au.dk
Requires-Python: >=3.7
License-File: LICENSE
Requires-Dist: ipynbname
Requires-Dist: jupyterlab (>=3.0)
